{
    "parents": [
        "minecraft:template/attached_stem"
    ],
    "pick_block": "minecraft:melon_seeds",
    "functions": {
        "minecraft:block_north_changed": [
            {
                "function": "minecraft:alter_block",
                "block": {
                    "name": "minecraft:melon_stem",
                    "properties": {
                        "age": "7"
                    }
                },
                "conditions": [
                    {
                        "blocks": [
                            {
                                "z": -1,
                                "block": {
                                    "name": "minecraft:melon",
                                    "inverse": true
                                }
                            },
                            {
                                "block": {
                                    "properties": {
                                        "facing": "north"
                                    }
                                }
                            }
                        ]
                    }
                ]
            }
        ],
        "minecraft:block_south_changed": [
            {
                "function": "minecraft:alter_block",
                "block": {
                    "name": "minecraft:melon_stem",
                    "properties": {
                        "age": "7"
                    }
                },
                "conditions": [
                    {
                        "blocks": [
                            {
                                "z": 1,
                                "block": {
                                    "name": "minecraft:melon",
                                    "inverse": true
                                }
                            },
                            {
                                "block": {
                                    "properties": {
                                        "facing": "south"
                                    }
                                }
                            }
                        ]
                    }
                ]
            }
        ],
        "minecraft:block_east_changed": [
            {
                "function": "minecraft:alter_block",
                "block": {
                    "name": "minecraft:melon_stem",
                    "properties": {
                        "age": "7"
                    }
                },
                "conditions": [
                    {
                        "blocks": [
                            {
                                "x": 1,
                                "block": {
                                    "name": "minecraft:melon",
                                    "inverse": true
                                }
                            },
                            {
                                "block": {
                                    "properties": {
                                        "facing": "east"
                                    }
                                }
                            }
                        ]
                    }
                ]
            }
        ],
        "minecraft:block_west_changed": [
            {
                "function": "minecraft:alter_block",
                "block": {
                    "name": "minecraft:melon_stem",
                    "properties": {
                        "age": "7"
                    }
                },
                "conditions": [
                    {
                        "blocks": [
                            {
                                "x": -1,
                                "block": {
                                    "name": "minecraft:melon",
                                    "inverse": true
                                }
                            },
                            {
                                "block": {
                                    "properties": {
                                        "facing": "west"
                                    }
                                }
                            }
                        ]
                    }
                ]
            }
        ]
    }
}