{
    "pick_block": "minecraft:snow_block",
    "mine_time": {
        "default": 1,
        "tool": {
            "tag": "minecraft:tool_tiers/strength/shovels/0"
        },
        "tools": [
            {
                "tag": "minecraft:tool_tiers/speed/shovels/0",
                "effect": {
                    "operation": "divide_player_mine_speed",
                    "value": 2,
                    "nesting": true
                }
            }
        ]
    },
    "blast_resistance": 1
}