{
    "shapes": [
        {
            "items": [
                [    "outline",    "outline",    "outline"    ],
                [    "outline",    "",    "outline"    ],
                [    "outline",    "bottom",    "outline"    ]
            ]
        }
    ],
    "ingredients": {
        "outline": {
            "name": "minecraft:cobblestone"
        },
        "bottom": {
            "name": "minecraft:redstone"
        }
    },
    "result": {
        "name": "minecraft:dropper"
    }
}