{
    "parent": "minecraft:2_items",
    "ingredients": {
        "item1": {
            "item": "minecraft:diamond_shovel"
        },
        "item2": {
            "item": "minecraft:diamond_shovel"
        }
    },
    "functions": [
        {
            "function": "minecraft:repair",
            "ingredients": [
                "item1",
                "item2"
            ],
            "bonus": 5
        }
    ],
    "result": {
        "item": "minecraft:diamond_shovel"
    },
    "group": "minecraft:repair_tool"
}