{
    "parent": "minecraft:banner/bottom_right_corner",
    "ingredients": {
        "banner": {
            "item": "minecraft:yellow_banner",
            "conditions": {
                "layers": {
                    "max": 15
                }
            }
        },
        "dye": {
            "item": "minecraft:ink_sack"
        }
    },
    "result": {
        "item": "minecraft:yellow_banner"
    },
    "group": "minecraft:banner_bottom_right_corner",
    "functions": [
        {
            "function": "minecraft:copy_nbt",
            "ingredient": "banner"
        },
        {
            "function": "minecraft:add_component",
            "banner": {
                "layer": {
                    "color": "black",
                    "pattern": "bottom_right_corner"
                }
            }
        }
    ]
}